{
    "dataType": [
        {"value": "images", "label": "Images"},
        {"value": "videos", "label": "Videos"},
        {"value": "audios", "label": "Audios"},
        {"value": "documents", "label": "Documents"},
        {"value": "others", "label": "Others"}
    ],
    "fileType": [
        {"value": "img", "label": "Img"},
        {"value": "png", "label": "Png"},
        {"value": "txt", "label":"Txt"},
        {"value": "csv", "label":"Csv"},
        {"value": "pdf", "label":"Pdf"},
        {"value": "doc", "label":"Doc"},
        {"value": "docx", "label": "Docx"},
        {"value": "xls", "label":"Xls"},
        {"value": "xlsx", "label": "Xlsx"},
        {"value": "ppt", "label":"Ppt"},
        {"value": "pptx", "label": "Pptx"},
        {"value": "mp3", "label":"Mp3"},
        {"value": "mp4", "label":"Mp4"},
        {"value": "avi", "label":"Avi"},
        {"value": "wmv", "label":"Wmv"},
        {"value": "mov", "label":"Mov"},
        {"value": "flv", "label":"Flv"},
        {"value": "zip", "label":"Zip"},
        {"value": "rar", "label":"Rar"},
        {"value": "7z", "label":"7z"},
        {"value": "tar", "label":"Tar"}
    ],
    "models": [
        {"value": "knn", "label": "K Nearest Neighbors"},
        {"value": "svm", "label": "Support Vector Machine"},
        {"value": "randomforest", "label": "Random Forest"},
        {"value": "logisticregression", "label": "Logistic Regression"},
        {"value": "naivebayes", "label": "Naive Bayes"},
        {"value": "decisiontree", "label": "Decision Tree"},
        {"value": "bagging", "label": "Bagging"},
        {"value": "gradientboosting", "label": "Gradient Boosting"},
        {"value": "xgboost", "label": "XGBoost"},
        {"value": "lightgbm", "label": "LightGBM"},
        {"value": "catboost", "label": "CatBoost"},
        {"value": "mlp", "label": "Multi-Layer Perceptron"},
        {"value": "dnn", "label": "Deep Neural Network"},
        {"value": "cnn", "label": "Convolutional Neural Network"},
        {"value": "rnn", "label": "Recurrent Neural Network"},
        {"value": "lstm", "label": "Long Short-Term Memory"},
        {"value": "gru", "label": "Gated Recurrent Unit"},
        {"value": "bert", "label": "Bert"},
        {"value": "transformer", "label": "Transformer"},
        {"value": "textcnn", "label": "TextCNN"},
        {"value": "word2vec", "label": "Word2Vec"},
        {"value": "wordembedding", "label": "Word Embedding"},
        {"value": "glove", "label": "Glove"},
        {"value": "fasttext", "label": "FastText"}
    ],
    "libraries": [
        {"value": "numpy", "label": "Numpy"},
        {"value": "scipy", "label": "SciPy"},
        {"value": "pandas", "label": "Pandas"},
        {"value": "sklearn", "label": "Sklearn"},
        {"value": "matplotlib", "label": "Matplotlib"},
        {"value": "seaborn", "label": "Seaborn"},
        {"value": "tensorflow", "label": "Tensorflow 2"},
        {"value": "keras", "label": "Keras"},
        {"value": "torch", "label": "Torch"},
        {"value": "torchvision", "label": "Torchvision"},
        {"value": "scikit-learn", "label": "Scikit-learn"}
    ]
}